FasterAPI/__init__.py
FasterAPI/__main__.py
FasterAPI/cli/__init__.py
FasterAPI/cli/module.py
FasterAPI/cli/project.py
FasterAPI/cli/templates/config.yaml.j2
FasterAPI/cli/templates/module/__init__.py.j2
FasterAPI/cli/templates/module/config.yaml.j2
FasterAPI/cli/templates/module/dependencies.py.j2
FasterAPI/cli/templates/module/router.py.j2
FasterAPI/cli/templates/module/schema.py.j2
FasterAPI/cli/templates/module/utils.py.j2
FasterAPI/cli/templates/serve.py.j2
FasterAPI/cli/templates/user/__init__.py.j2
FasterAPI/cli/templates/user/config.yaml.j2
FasterAPI/cli/templates/user/dependencies.py.j2
FasterAPI/cli/templates/user/router.py.j2
FasterAPI/cli/templates/user/schemas.py.j2
FasterAPI/cli/templates/user/utils.py.j2
fasterapi-1.0.4.dist-info/entry_points.txt
fasterapi-1.0.4.dist-info/METADATA
fasterapi-1.0.4.dist-info/WHEEL
fasterapi-1.0.4.dist-info/RECORD
