Metadata-Version: 2.1
Name: FasterAPI
Version: 1.0.4
Summary: 
Author: ulfaric
Author-email: ryf0510@live.com
Requires-Python: >=3.8,<4.0
Classifier: Programming Language :: Python :: 3
Classifier: Programming Language :: Python :: 3.8
Classifier: Programming Language :: Python :: 3.9
Classifier: Programming Language :: Python :: 3.10
Classifier: Programming Language :: Python :: 3.11
Classifier: Programming Language :: Python :: 3.12
Requires-Dist: alembic (>=1.13.1,<2.0.0)
Requires-Dist: bcrypt (==4.0.1)
Requires-Dist: colorlog (>=6.8.2,<7.0.0)
Requires-Dist: fastapi[all] (>=0.110.0,<0.111.0)
Requires-Dist: opentelemetry-api (>=1.23.0,<2.0.0)
Requires-Dist: opentelemetry-exporter-jaeger (>=1.21.0,<2.0.0)
Requires-Dist: opentelemetry-instrumentation (>=0.44b0,<0.45)
Requires-Dist: opentelemetry-instrumentation-fastapi (>=0.44b0,<0.45)
Requires-Dist: opentelemetry-sdk (>=1.23.0,<2.0.0)
Requires-Dist: passlib[bcrypt] (>=1.7.4,<2.0.0)
Requires-Dist: python-jose[cryptography] (>=3.3.0,<4.0.0)
Requires-Dist: pyyaml (>=6.0.1,<7.0.0)
Requires-Dist: sqlalchemy (>=2.0.28,<3.0.0)
Requires-Dist: typer[all] (>=0.10.0,<0.11.0)
Project-URL: documentation, https://ulfaric.github.io/FasterAPI/
Project-URL: github, https://github.com/ulfaric/FasterAPI/issues
